clandestino_mongo/__init__.py
clandestino_mongo/infra.py
clandestino_mongo/ref.py
clandestino_mongo/repository.py
clandestino_mongo-0.1.1.dist-info/LICENSE
clandestino_mongo-0.1.1.dist-info/METADATA
clandestino_mongo-0.1.1.dist-info/WHEEL
clandestino_mongo-0.1.1.dist-info/RECORD
